{"Case": "Gamma 2 Case", "IsBuff": true, "ImageUrl": "https://steamcommunity-a.akamaihd.net/economy/image/-9a81dlWLwJ2UUGcVs_nsVtzdOEdtWwKGZZLQHTxDZ7I56KU0Zwwo4NUX4oFJZEHLbXU5A1PIYQNqhpOSV-fRPasw8rsVFx5KAVo5PSkKV4xhfGfKTgVvIXlxNPSwaOmMLiGwzgJvJMniO-Zoo_z2wXg-EVvfSmtc78HsNoy/256fx256f", "Profit": 0.009811722080136401, "ProfitPercents": {"Covert": 0.004293158567774936, "Classified": 0.0023683930093776643, "Restricted": 0.0005927109974424553, "Mil_Spec": 0, "Contraband": 0.002557459505541345}, "PercentReceive": {"Contraband": 0.0025575447570332483, "Covert": 0.00639386189258312, "Classified": 0.0319693094629156, "Restricted": 0.159846547314578, "Mil_Spec": 0.7992327365728901}, "CaseCost": 4.3, "KeyCost": 2.5, "ROI": 0.40189334884760713, "RarityROIPercents": {"Contraband": 0.8089083311530759, "Covert": 0.04331812467846626, "Classified": 0.04716435780214934, "Restricted": 0.04486875289358569, "Mil_Spec": 0.05574043347272281}, "RarityValue": {"Covert": 11.7080797, "Classified": 2.549528929267733, "Restricted": 0.48508742132029603, "Mil_Spec": 0.12052478124670159, "Contraband": 546.5820185795224}, "IsCaseEstimate": false, "KnifeCosts": {"Bayonet | Autotronic": {"FactoryNew": 888.3599999999999, "StatTrak\u2122 FactoryNew": 881.6699999999998, "MinimalWear": 539.66, "StatTrak\u2122 MinimalWear": 601.38, "FieldTested": 437.01, "StatTrak\u2122 FieldTested": 429.00999999999993, "WellWorn": 426.89, "StatTrak\u2122 WellWorn": 451.08, "BattleScarred": 416.63999999999993, "StatTrak\u2122 BattleScarred": 437.14, "totalItemValue": 478.83162}, "Bayonet | Lore": {"FactoryNew": 956.16, "StatTrak\u2122 FactoryNew": 984.18, "MinimalWear": 649.29, "StatTrak\u2122 MinimalWear": 641.0899999999999, "FieldTested": 450.91999999999996, "StatTrak\u2122 FieldTested": 457.5799999999999, "WellWorn": 434.13, "StatTrak\u2122 WellWorn": 505.75999999999993, "BattleScarred": 364.96999999999997, "StatTrak\u2122 BattleScarred": 371.8, "totalItemValue": 556.2490869}, "Bayonet | Gamma Doppler": {"FactoryNew": 820.15, "StatTrak\u2122 FactoryNew": 906.27, "MinimalWear": 833.8199999999999, "StatTrak\u2122 MinimalWear": 1220.2477390058998, "totalItemValue": 830.3789286343218}, "Bayonet | Black Laminate": {"FactoryNew": 505.75999999999993, "StatTrak\u2122 FactoryNew": 578.2099999999999, "MinimalWear": 314.39, "StatTrak\u2122 MinimalWear": 327.98999999999995, "FieldTested": 296.48999999999995, "StatTrak\u2122 FieldTested": 296.34, "WellWorn": 269.22, "StatTrak\u2122 WellWorn": 293.82, "BattleScarred": 262.65, "StatTrak\u2122 BattleScarred": 280.08, "totalItemValue": 296.51297999999997}, "Bayonet | Freehand": {"FactoryNew": 364.83, "StatTrak\u2122 FactoryNew": 403.11, "MinimalWear": 329.90999999999997, "StatTrak\u2122 MinimalWear": 339.31, "FieldTested": 277.14, "StatTrak\u2122 FieldTested": 286.09999999999997, "WellWorn": 252.87999999999997, "StatTrak\u2122 WellWorn": 303.46, "BattleScarred": 266.48, "StatTrak\u2122 BattleScarred": 270.65, "totalItemValue": 312.93973869999996}, "Bayonet | Bright Water": {"FactoryNew": 329.28999999999996, "StatTrak\u2122 FactoryNew": 341.66, "MinimalWear": 282.95, "StatTrak\u2122 MinimalWear": 304.82, "FieldTested": 233.73999999999998, "StatTrak\u2122 FieldTested": 238.52999999999997, "WellWorn": 229.64, "StatTrak\u2122 WellWorn": 246.04999999999998, "BattleScarred": 232.23999999999998, "StatTrak\u2122 BattleScarred": 259.71999999999997, "totalItemValue": 269.2588984}, "Flip Knife | Autotronic": {"FactoryNew": 571.01, "StatTrak\u2122 FactoryNew": 505.75999999999993, "MinimalWear": 341.72999999999996, "StatTrak\u2122 MinimalWear": 341.59, "FieldTested": 266.76, "StatTrak\u2122 FieldTested": 264.5, "WellWorn": 244.67999999999998, "StatTrak\u2122 WellWorn": 272.02, "BattleScarred": 228.27999999999997, "StatTrak\u2122 BattleScarred": 227.73, "totalItemValue": 291.1931303}, "Flip Knife | Gamma Doppler": {"FactoryNew": 598.7099999999999, "StatTrak\u2122 FactoryNew": 610.26, "MinimalWear": 635.4799999999999, "StatTrak\u2122 MinimalWear": 601.4499999999999, "totalItemValue": 601.0568440000001}, "Flip Knife | Lore": {"FactoryNew": 547.9200000000001, "StatTrak\u2122 FactoryNew": 546.77, "MinimalWear": 392.03, "StatTrak\u2122 MinimalWear": 407.2099999999999, "FieldTested": 304.35, "StatTrak\u2122 FieldTested": 312, "WellWorn": 271.88, "StatTrak\u2122 WellWorn": 272.02, "BattleScarred": 234.89999999999998, "StatTrak\u2122 BattleScarred": 259.44, "totalItemValue": 350.40179749999993}, "Flip Knife | Bright Water": {"FactoryNew": 230.19, "StatTrak\u2122 FactoryNew": 247.34, "MinimalWear": 198.19999999999996, "StatTrak\u2122 MinimalWear": 213.03, "FieldTested": 187.06, "StatTrak\u2122 FieldTested": 188.64, "WellWorn": 169.35999999999999, "StatTrak\u2122 WellWorn": 198.82, "BattleScarred": 175.64999999999998, "StatTrak\u2122 BattleScarred": 174.97, "totalItemValue": 199.8326518}, "Flip Knife | Black Laminate": {"FactoryNew": 333.52, "StatTrak\u2122 FactoryNew": 326.69, "MinimalWear": 207.63999999999996, "StatTrak\u2122 MinimalWear": 205.04, "FieldTested": 195.45, "StatTrak\u2122 FieldTested": 200.73, "WellWorn": 177.63, "StatTrak\u2122 WellWorn": 181.8, "BattleScarred": 177.7, "StatTrak\u2122 BattleScarred": 177.56, "totalItemValue": 195.59008999999998}, "Flip Knife | Freehand": {"FactoryNew": 232.23999999999998, "StatTrak\u2122 FactoryNew": 259.71999999999997, "MinimalWear": 217.06999999999996, "StatTrak\u2122 MinimalWear": 222.88, "FieldTested": 197.38, "StatTrak\u2122 FieldTested": 210.16, "WellWorn": 193.82999999999998, "StatTrak\u2122 WellWorn": 182.0864850959, "BattleScarred": 204.14999999999998, "StatTrak\u2122 BattleScarred": 204.76999999999998, "totalItemValue": 212.38646161561428}, "Gut Knife | Lore": {"FactoryNew": 252.87999999999997, "StatTrak\u2122 FactoryNew": 311.42, "MinimalWear": 191.3, "StatTrak\u2122 MinimalWear": 229.64, "FieldTested": 161.97, "StatTrak\u2122 FieldTested": 161.29999999999998, "WellWorn": 167.58, "StatTrak\u2122 WellWorn": 217.40941805580002, "BattleScarred": 135.32999999999998, "StatTrak\u2122 BattleScarred": 166.89999999999998, "totalItemValue": 180.549332043598}, "Gut Knife | Gamma Doppler": {"FactoryNew": 258.21, "StatTrak\u2122 FactoryNew": 272.35999999999996, "MinimalWear": 267.91999999999996, "StatTrak\u2122 MinimalWear": 2733.85, "totalItemValue": 269.055856}, "Gut Knife | Autotronic": {"FactoryNew": 308.92, "StatTrak\u2122 FactoryNew": 332.78, "MinimalWear": 183.17, "StatTrak\u2122 MinimalWear": 204.9, "FieldTested": 161.57, "StatTrak\u2122 FieldTested": 172.77, "WellWorn": 163.62, "StatTrak\u2122 WellWorn": 171.0911640908859, "BattleScarred": 150.35999999999999, "StatTrak\u2122 BattleScarred": 166.76, "totalItemValue": 172.71274526001355}, "Gut Knife | Black Laminate": {"FactoryNew": 159.25, "StatTrak\u2122 FactoryNew": 410.78999999999996, "MinimalWear": 103.89, "StatTrak\u2122 MinimalWear": 143.52999999999997, "FieldTested": 96.49999999999999, "StatTrak\u2122 FieldTested": 128.48999999999998, "WellWorn": 95.67999999999999, "StatTrak\u2122 WellWorn": 116.19, "BattleScarred": 95.75999999999999, "StatTrak\u2122 BattleScarred": 108.6, "totalItemValue": 103.30022999999998}, "Gut Knife | Freehand": {"FactoryNew": 116.19, "StatTrak\u2122 FactoryNew": 140.93, "MinimalWear": 107.99, "StatTrak\u2122 MinimalWear": 122.82, "FieldTested": 91.04, "StatTrak\u2122 FieldTested": 113.16999999999999, "WellWorn": 95.41, "StatTrak\u2122 WellWorn": 97.59, "BattleScarred": 88.85, "StatTrak\u2122 BattleScarred": 89.37872006670536, "totalItemValue": 103.7048500321234}, "Gut Knife | Bright Water": {"FactoryNew": 105.25, "StatTrak\u2122 FactoryNew": 139.14999999999998, "MinimalWear": 99.64999999999999, "StatTrak\u2122 MinimalWear": 110.03999999999999, "FieldTested": 90.41999999999999, "StatTrak\u2122 FieldTested": 97.05, "WellWorn": 90.9, "StatTrak\u2122 WellWorn": 109.35, "BattleScarred": 84.48, "StatTrak\u2122 BattleScarred": 101.84, "totalItemValue": 97.4928405}, "Karambit | Autotronic": {"FactoryNew": 1932.2799999999997, "StatTrak\u2122 FactoryNew": 2035.08, "MinimalWear": 1189.22, "StatTrak\u2122 MinimalWear": 1120.6, "FieldTested": 943.11, "StatTrak\u2122 FieldTested": 901.76, "WellWorn": 840.66, "StatTrak\u2122 WellWorn": 840.66, "BattleScarred": 676.6299999999999, "StatTrak\u2122 BattleScarred": 731.3, "totalItemValue": 1000.5854011}, "Karambit | Gamma Doppler": {"FactoryNew": 1647.1399999999999, "StatTrak\u2122 FactoryNew": 1605.9299999999998, "MinimalWear": 1530.6099999999997, "StatTrak\u2122 MinimalWear": 1640.31, "totalItemValue": 1639.265757}, "Karambit | Lore": {"FactoryNew": 2186.9399999999996, "StatTrak\u2122 FactoryNew": 2187.08, "MinimalWear": 1283.2, "StatTrak\u2122 MinimalWear": 1257.57, "FieldTested": 772.17, "StatTrak\u2122 FieldTested": 815.9799999999999, "WellWorn": 737.87, "StatTrak\u2122 WellWorn": 731.3, "BattleScarred": 546.77, "StatTrak\u2122 BattleScarred": 567.27, "totalItemValue": 1057.3127885000001}, "Karambit | Black Laminate": {"FactoryNew": 1148.1499999999999, "StatTrak\u2122 FactoryNew": 1148.2199999999998, "MinimalWear": 806.3299999999999, "StatTrak\u2122 MinimalWear": 857.06, "FieldTested": 748.8, "StatTrak\u2122 FieldTested": 724.3299999999999, "WellWorn": 683.32, "StatTrak\u2122 WellWorn": 691.53, "BattleScarred": 683.4599999999999, "StatTrak\u2122 BattleScarred": 708.68, "totalItemValue": 749.4288799999999}, "Karambit | Freehand": {"FactoryNew": 688.86, "StatTrak\u2122 FactoryNew": 724.3299999999999, "MinimalWear": 613, "StatTrak\u2122 MinimalWear": 626.05, "FieldTested": 546.6999999999999, "StatTrak\u2122 FieldTested": 535.83, "WellWorn": 526.81, "StatTrak\u2122 WellWorn": 505.75999999999993, "BattleScarred": 536.78, "StatTrak\u2122 BattleScarred": 560.3, "totalItemValue": 598.7626964}, "Karambit | Bright Water": {"FactoryNew": 662.9599999999999, "StatTrak\u2122 FactoryNew": 683.4599999999999, "MinimalWear": 574.04, "StatTrak\u2122 MinimalWear": 574.11, "FieldTested": 527.43, "StatTrak\u2122 FieldTested": 519.43, "WellWorn": 485.25999999999993, "StatTrak\u2122 WellWorn": 512.6, "BattleScarred": 476.50999999999993, "StatTrak\u2122 BattleScarred": 487.38, "totalItemValue": 567.7753683}, "M9 Bayonet | Gamma Doppler": {"FactoryNew": 1312.2499999999998, "StatTrak\u2122 FactoryNew": 1291.6699999999998, "MinimalWear": 1230.0899999999997, "StatTrak\u2122 MinimalWear": 1312.2499999999998, "totalItemValue": 1307.5322179999998}, "M9 Bayonet | Autotronic": {"FactoryNew": 1544.49, "StatTrak\u2122 FactoryNew": 1731.34, "MinimalWear": 1107.2099999999998, "StatTrak\u2122 MinimalWear": 1031.82, "FieldTested": 906.27, "StatTrak\u2122 FieldTested": 867.31, "WellWorn": 820.15, "StatTrak\u2122 WellWorn": 833.8199999999999, "BattleScarred": 731.1, "StatTrak\u2122 BattleScarred": 722.9599999999999, "totalItemValue": 951.4859425999999}, "M9 Bayonet | Black Laminate": {"FactoryNew": 939.0799999999998, "StatTrak\u2122 FactoryNew": 940.6499999999999, "MinimalWear": 697.13, "StatTrak\u2122 MinimalWear": 697.06, "FieldTested": 668.15, "StatTrak\u2122 FieldTested": 635.62, "WellWorn": 641.4999999999999, "StatTrak\u2122 WellWorn": 615.12, "BattleScarred": 642.3199999999999, "StatTrak\u2122 BattleScarred": 666.85, "totalItemValue": 671.3932}, "M9 Bayonet | Lore": {"FactoryNew": 2774.79, "StatTrak\u2122 FactoryNew": 2744.7799999999997, "MinimalWear": 1884.7099999999998, "StatTrak\u2122 MinimalWear": 1859.0199999999998, "FieldTested": 887.8199999999998, "StatTrak\u2122 FieldTested": 840.66, "WellWorn": 758.6399999999999, "StatTrak\u2122 WellWorn": 846.13, "BattleScarred": 513.9599999999999, "StatTrak\u2122 BattleScarred": 546.63, "totalItemValue": 1332.8995599999998}, "M9 Bayonet | Bright Water": {"FactoryNew": 593.93, "StatTrak\u2122 FactoryNew": 613.6800000000001, "MinimalWear": 531.73, "StatTrak\u2122 MinimalWear": 559.69, "FieldTested": 461.74999999999994, "StatTrak\u2122 FieldTested": 437.41999999999996, "WellWorn": 409.86999999999995, "StatTrak\u2122 WellWorn": 409.94, "BattleScarred": 394.77, "StatTrak\u2122 BattleScarred": 409.94, "totalItemValue": 505.96690229999996}, "M9 Bayonet | Freehand": {"FactoryNew": 577.39, "StatTrak\u2122 FactoryNew": 590.4399999999999, "MinimalWear": 512.12, "StatTrak\u2122 MinimalWear": 510.96, "FieldTested": 442.80999999999995, "StatTrak\u2122 FieldTested": 450.4, "WellWorn": 430.58, "StatTrak\u2122 WellWorn": 451.08, "BattleScarred": 408.29999999999995, "StatTrak\u2122 BattleScarred": 420.59000000000003, "totalItemValue": 493.6037615}}, "ItemCosts": {"Covert": {"AK-47 | Neon Revolution": {"FactoryNew": 55.120000000000005, "StatTrak\u2122 FactoryNew": 136.49, "MinimalWear": 20.779999999999998, "StatTrak\u2122 MinimalWear": 58.089999999999996, "FieldTested": 11.87, "StatTrak\u2122 FieldTested": 32.38, "WellWorn": 19.740000000000002, "StatTrak\u2122 WellWorn": 39.78, "BattleScarred": 11.83, "StatTrak\u2122 BattleScarred": 33.35, "totalItemValue": 19.5838894}, "FAMAS | Roll Cage": {"FactoryNew": 13.2, "StatTrak\u2122 FactoryNew": 55.22, "MinimalWear": 5, "StatTrak\u2122 MinimalWear": 12.7, "FieldTested": 2.4600000000000004, "StatTrak\u2122 FieldTested": 6.31, "WellWorn": 2.11, "StatTrak\u2122 WellWorn": 5.69, "BattleScarred": 2.1300000000000003, "StatTrak\u2122 BattleScarred": 5.470000000000001, "totalItemValue": 3.83227}}, "Classified": {"Tec-9 | Fuel Injector": {"FactoryNew": 10.389999999999999, "StatTrak\u2122 FactoryNew": 33.22, "MinimalWear": 3.76, "StatTrak\u2122 MinimalWear": 9.84, "FieldTested": 1.93, "StatTrak\u2122 FieldTested": 4.88, "WellWorn": 1.6700000000000002, "StatTrak\u2122 WellWorn": 3.98, "BattleScarred": 1.76, "StatTrak\u2122 BattleScarred": 3.98, "totalItemValue": 2.93612}, "AUG | Syd Mead": {"FactoryNew": 7.2, "StatTrak\u2122 FactoryNew": 17.77, "MinimalWear": 3, "StatTrak\u2122 MinimalWear": 6.82, "FieldTested": 1.39, "StatTrak\u2122 FieldTested": 3.0100000000000002, "WellWorn": 2.19, "StatTrak\u2122 WellWorn": 3.54, "BattleScarred": 1.34, "StatTrak\u2122 BattleScarred": 2.85, "totalItemValue": 2.4049934}, "MP9 | Airlock": {"FactoryNew": 7.590000000000001, "StatTrak\u2122 FactoryNew": 19, "MinimalWear": 3.2, "StatTrak\u2122 MinimalWear": 6.5600000000000005, "FieldTested": 1.57, "StatTrak\u2122 FieldTested": 3.31, "WellWorn": 1.3149335596, "StatTrak\u2122 WellWorn": 2.3965724554, "BattleScarred": 1.62, "StatTrak\u2122 BattleScarred": 2.91, "totalItemValue": 2.3074733878032}}, "Restricted": {"Desert Eagle | Directive": {"FactoryNew": 8.89, "StatTrak\u2122 FactoryNew": 35.54, "MinimalWear": 1.09, "StatTrak\u2122 MinimalWear": 5.56, "FieldTested": 0.31, "StatTrak\u2122 FieldTested": 1.6, "WellWorn": 0.26999999999999996, "StatTrak\u2122 WellWorn": 1.76, "BattleScarred": 0.25, "StatTrak\u2122 BattleScarred": 1.3785593770000002, "totalItemValue": 0.55126312368508}, "Glock-18 | Weasel": {"FactoryNew": 1.6900000000000002, "StatTrak\u2122 FactoryNew": 9.649999999999999, "MinimalWear": 0.55, "StatTrak\u2122 MinimalWear": 2.47, "FieldTested": 0.26, "StatTrak\u2122 FieldTested": 0.93, "WellWorn": 0.24000000000000002, "StatTrak\u2122 WellWorn": 1.03, "BattleScarred": 0.24000000000000002, "StatTrak\u2122 BattleScarred": 0.93, "totalItemValue": 0.48657000000000006}, "SG 553 | Triarch": {"FactoryNew": 1.95, "StatTrak\u2122 FactoryNew": 4.91, "MinimalWear": 0.52, "StatTrak\u2122 MinimalWear": 1.33, "FieldTested": 0.31, "StatTrak\u2122 FieldTested": 0.42, "WellWorn": 0.24000000000000002, "StatTrak\u2122 WellWorn": 0.37, "BattleScarred": 0.24000000000000002, "StatTrak\u2122 BattleScarred": 0.36, "totalItemValue": 0.41859}, "SCAR-20 | Powercore": {"FactoryNew": 1.1300000000000001, "StatTrak\u2122 FactoryNew": 3.42, "MinimalWear": 0.47, "StatTrak\u2122 MinimalWear": 0.95, "FieldTested": 0.29692048120000003, "StatTrak\u2122 FieldTested": 0.4, "WellWorn": 0.23, "StatTrak\u2122 WellWorn": 0.37, "BattleScarred": 0.24000000000000002, "StatTrak\u2122 BattleScarred": 0.39, "totalItemValue": 0.36583538291640005}, "MAG-7 | Petroglyph": {"FactoryNew": 1.05, "StatTrak\u2122 FactoryNew": 2.54, "MinimalWear": 0.43000000000000005, "StatTrak\u2122 MinimalWear": 0.94, "FieldTested": 0.3, "StatTrak\u2122 FieldTested": 0.48000000000000004, "WellWorn": 0.38000000000000006, "StatTrak\u2122 WellWorn": 0.52, "totalItemValue": 0.6031786}}, "Mil_Spec": {"P90 | Grim": {"FactoryNew": 0.7000000000000001, "StatTrak\u2122 FactoryNew": 2.7600000000000002, "MinimalWear": 0.2, "StatTrak\u2122 MinimalWear": 0.71, "FieldTested": 0.1, "StatTrak\u2122 FieldTested": 0.24000000000000002, "WellWorn": 0.16, "StatTrak\u2122 WellWorn": 1.19, "BattleScarred": 0.1, "StatTrak\u2122 BattleScarred": 0.23, "totalItemValue": 0.19683600000000004}, "Negev | Dazzle": {"MinimalWear": 0.21, "StatTrak\u2122 MinimalWear": 1.1, "FieldTested": 0.08, "StatTrak\u2122 FieldTested": 0.11, "WellWorn": 0.07423012030000001, "StatTrak\u2122 WellWorn": 0.26, "BattleScarred": 0.05, "StatTrak\u2122 BattleScarred": 0.09, "totalItemValue": 0.094796527981779}, "Five-SeveN | Scumbria": {"FactoryNew": 0.3, "StatTrak\u2122 FactoryNew": 1.48, "MinimalWear": 0.1, "StatTrak\u2122 MinimalWear": 0.26, "FieldTested": 0.07, "StatTrak\u2122 FieldTested": 0.1, "WellWorn": 0.05, "StatTrak\u2122 WellWorn": 0.09, "BattleScarred": 0.05, "StatTrak\u2122 BattleScarred": 0.12000000000000001, "totalItemValue": 0.08655}, "XM1014 | Slipstream": {"FactoryNew": 0.24000000000000002, "StatTrak\u2122 FactoryNew": 0.94, "MinimalWear": 0.12000000000000001, "StatTrak\u2122 MinimalWear": 0.5399999999999999, "FieldTested": 0.07, "StatTrak\u2122 FieldTested": 0.23, "WellWorn": 0.08, "StatTrak\u2122 WellWorn": 0.35000000000000003, "BattleScarred": 0.08, "StatTrak\u2122 BattleScarred": 0.35000000000000003, "totalItemValue": 0.15885670000000005}, "CZ75-Auto | Imprint": {"FactoryNew": 0.34, "StatTrak\u2122 FactoryNew": 1.4100000000000001, "MinimalWear": 0.106043029, "StatTrak\u2122 MinimalWear": 0.26999999999999996, "FieldTested": 0.07423012030000001, "StatTrak\u2122 FieldTested": 0.14, "WellWorn": 0.05, "StatTrak\u2122 WellWorn": 0.1, "BattleScarred": 0.07, "StatTrak\u2122 BattleScarred": 0.09, "totalItemValue": 0.09418163999310002}, "UMP-45 | Briefing": {"FactoryNew": 0.22, "StatTrak\u2122 FactoryNew": 0.9700000000000001, "MinimalWear": 0.1, "StatTrak\u2122 MinimalWear": 0.29000000000000004, "FieldTested": 0.07, "StatTrak\u2122 FieldTested": 0.106043029, "WellWorn": 0.05, "StatTrak\u2122 WellWorn": 0.09, "BattleScarred": 0.05, "StatTrak\u2122 BattleScarred": 0.09, "totalItemValue": 0.083299419957}, "G3SG1 | Ventilator": {"FactoryNew": 0.19000000000000003, "StatTrak\u2122 FactoryNew": 0.65, "MinimalWear": 0.09, "StatTrak\u2122 MinimalWear": 0.32, "FieldTested": 0.07423012030000001, "StatTrak\u2122 FieldTested": 0.09543872610000001, "WellWorn": 0.07, "StatTrak\u2122 WellWorn": 0.17, "totalItemValue": 0.129153180795032}}}, "Items": {"AK-47 | Neon Revolution": {"Name": "AK-47 | Neon Revolution", "FloatMin": 0, "FloatMax": 80, "ImageUrl": "https://steamcdn-a.akamaihd.net/apps/730/icons/econ/default_generated/weapon_ak47_cu_ak47_anarchy_light_large.6e98f0c6fcb81aaeca03c56eed68962f50c9ef94.png", "Variations": 1, "Rarity": 11, "IsKnife": false, "ItemCollectionId": 24}, "FAMAS | Roll Cage": {"Name": "FAMAS | Roll Cage", "FloatMin": 0, "FloatMax": 100, "ImageUrl": "https://steamcdn-a.akamaihd.net/apps/730/icons/econ/default_generated/weapon_famas_gs_famas_rally_light_large.538baee44eb772de95029e4267ea9c41101bbc94.png", "Variations": 1, "Rarity": 11, "IsKnife": false, "ItemCollectionId": 24}, "Tec-9 | Fuel Injector": {"Name": "Tec-9 | Fuel Injector", "FloatMin": 0, "FloatMax": 100, "ImageUrl": "https://steamcdn-a.akamaihd.net/apps/730/icons/econ/default_generated/weapon_tec9_gs_tec9_supercharged_light_large.e3ebc20f10eae02790fe95703b6099acca1d1809.png", "Variations": 1, "Rarity": 8, "IsKnife": false, "ItemCollectionId": 24}, "AUG | Syd Mead": {"Name": "AUG | Syd Mead", "FloatMin": 0, "FloatMax": 80, "ImageUrl": "https://steamcdn-a.akamaihd.net/apps/730/icons/econ/default_generated/weapon_aug_gs_aug_syd_mead_light_large.333597e0555639f5d77541c363a9bb38d95055f3.png", "Variations": 1, "Rarity": 8, "IsKnife": false, "ItemCollectionId": 24}, "MP9 | Airlock": {"Name": "MP9 | Airlock", "FloatMin": 0, "FloatMax": 100, "ImageUrl": "https://steamcdn-a.akamaihd.net/apps/730/icons/econ/default_generated/weapon_mp9_cu_mp9_narcis_light_large.c63eaf3fab8c65ec3ab22da8205cbe3c51366d7a.png", "Variations": 1, "Rarity": 8, "IsKnife": false, "ItemCollectionId": 24}, "Desert Eagle | Directive": {"Name": "Desert Eagle | Directive", "FloatMin": 6, "FloatMax": 100, "ImageUrl": "https://steamcdn-a.akamaihd.net/apps/730/icons/econ/default_generated/weapon_deagle_aq_desert_eagle_constable_light_large.fb2f2673dd3997a21bff9129e0d2e294c03095e8.png", "Variations": 1, "Rarity": 5, "IsKnife": false, "ItemCollectionId": 24}, "Glock-18 | Weasel": {"Name": "Glock-18 | Weasel", "FloatMin": 0, "FloatMax": 100, "ImageUrl": "https://steamcdn-a.akamaihd.net/apps/730/icons/econ/default_generated/weapon_glock_cu_glock18_weasel_light_large.e02e6e5196ebdee47c595799ff011dd645147505.png", "Variations": 1, "Rarity": 5, "IsKnife": false, "ItemCollectionId": 24}, "SG 553 | Triarch": {"Name": "SG 553 | Triarch", "FloatMin": 0, "FloatMax": 100, "ImageUrl": "https://steamcdn-a.akamaihd.net/apps/730/icons/econ/default_generated/weapon_sg556_cu_sg556_triarch_light_large.3ea74bea530adda100d25911372ca313ea99453a.png", "Variations": 1, "Rarity": 5, "IsKnife": false, "ItemCollectionId": 24}, "SCAR-20 | Powercore": {"Name": "SCAR-20 | Powercore", "FloatMin": 0, "FloatMax": 100, "ImageUrl": "https://steamcdn-a.akamaihd.net/apps/730/icons/econ/default_generated/weapon_scar20_gs_scar20_powercore_light_large.74bcd65b1a4a52dd397ede5aa59b860ca4c38939.png", "Variations": 1, "Rarity": 5, "IsKnife": false, "ItemCollectionId": 24}, "MAG-7 | Petroglyph": {"Name": "MAG-7 | Petroglyph", "FloatMin": 0, "FloatMax": 44, "ImageUrl": "https://steamcdn-a.akamaihd.net/apps/730/icons/econ/default_generated/weapon_mag7_cu_mag7_tribal_light_large.c226728af447f07808ea5954eb9a24528092d972.png", "Variations": 1, "Rarity": 5, "IsKnife": false, "ItemCollectionId": 24}, "P90 | Grim": {"Name": "P90 | Grim", "FloatMin": 0, "FloatMax": 80, "ImageUrl": "https://steamcdn-a.akamaihd.net/apps/730/icons/econ/default_generated/weapon_p90_cu_p90_grimm_light_large.59514d7b54f637f314329bb3fef1c7ffd1b153ba.png", "Variations": 1, "Rarity": 2, "IsKnife": false, "ItemCollectionId": 24}, "Negev | Dazzle": {"Name": "Negev | Dazzle", "FloatMin": 10, "FloatMax": 65, "ImageUrl": "https://steamcdn-a.akamaihd.net/apps/730/icons/econ/default_generated/weapon_negev_hy_negev_dazzle_light_large.3558ece2a70252dcaa8ea9e324539ae1a4fc1bc0.png", "Variations": 1, "Rarity": 2, "IsKnife": false, "ItemCollectionId": 24}, "Five-SeveN | Scumbria": {"Name": "Five-SeveN | Scumbria", "FloatMin": 0, "FloatMax": 100, "ImageUrl": "https://steamcdn-a.akamaihd.net/apps/730/icons/econ/default_generated/weapon_fiveseven_aq_five_seven_scumbria_light_large.bc05fc6435b84525a0ab140bc72e032a98dab710.png", "Variations": 1, "Rarity": 2, "IsKnife": false, "ItemCollectionId": 24}, "XM1014 | Slipstream": {"Name": "XM1014 | Slipstream", "FloatMin": 0, "FloatMax": 50, "ImageUrl": "https://steamcdn-a.akamaihd.net/apps/730/icons/econ/default_generated/weapon_xm1014_hy_xm1014_fractal_blue_light_large.e9720fb7b5928db8bcf79d62850af5bf475b9ec5.png", "Variations": 1, "Rarity": 2, "IsKnife": false, "ItemCollectionId": 24}, "CZ75-Auto | Imprint": {"Name": "CZ75-Auto | Imprint", "FloatMin": 0, "FloatMax": 100, "ImageUrl": "https://steamcdn-a.akamaihd.net/apps/730/icons/econ/default_generated/weapon_cz75a_gs_cz75_tread_light_large.8c276db730bb33477aaa52f7a23825f295e14364.png", "Variations": 1, "Rarity": 2, "IsKnife": false, "ItemCollectionId": 24}, "UMP-45 | Briefing": {"Name": "UMP-45 | Briefing", "FloatMin": 0, "FloatMax": 100, "ImageUrl": "https://steamcdn-a.akamaihd.net/apps/730/icons/econ/default_generated/weapon_ump45_cu_ump45_metritera_light_large.46ac4388a9651c555ec6849358b85f60a87c328d.png", "Variations": 1, "Rarity": 2, "IsKnife": false, "ItemCollectionId": 24}, "G3SG1 | Ventilator": {"Name": "G3SG1 | Ventilator", "FloatMin": 0, "FloatMax": 45, "ImageUrl": "https://steamcdn-a.akamaihd.net/apps/730/icons/econ/default_generated/weapon_g3sg1_gs_g3sg1_ventilator_light_large.5cd3643d4d9cd0599e25a1302e788611bd9a0023.png", "Variations": 1, "Rarity": 2, "IsKnife": false, "ItemCollectionId": 24}, "Bayonet | Autotronic": {"Name": "Bayonet | Autotronic", "FloatMin": 0, "FloatMax": 85, "ImageUrl": "https://steamcdn-a.akamaihd.net/apps/730/icons/econ/default_generated/weapon_bayonet_gs_bayonet_autotronic_light_large.4b7f809f4ee434dff8f270b041100012f39c5ebe.png", "Variations": 1, "Rarity": 11, "IsKnife": true, "ItemCollectionId": 24}, "Bayonet | Lore": {"Name": "Bayonet | Lore", "FloatMin": 0, "FloatMax": 65, "ImageUrl": "https://steamcdn-a.akamaihd.net/apps/730/icons/econ/default_generated/weapon_bayonet_cu_bayonet_lore_light_large.372c7e0ec654f3be5d53e87cbbac3ab160c8c76e.png", "Variations": 1, "Rarity": 11, "IsKnife": true, "ItemCollectionId": 24}, "Bayonet | Gamma Doppler": {"Name": "Bayonet | Gamma Doppler", "FloatMin": 0, "FloatMax": 8, "ImageUrl": "https://steamcdn-a.akamaihd.net/apps/730/icons/econ/default_generated/weapon_bayonet_am_gamma_doppler_phase1_light_large.02bbfec15811bc1679479107af0cf5c6652e40f1.png", "Variations": 1, "Rarity": 11, "IsKnife": true, "ItemCollectionId": 24}, "Bayonet | Black Laminate": {"Name": "Bayonet | Black Laminate", "FloatMin": 0, "FloatMax": 100, "ImageUrl": "https://steamcdn-a.akamaihd.net/apps/730/icons/econ/default_generated/weapon_bayonet_cu_bayonet_stonewash_light_large.0f931ca831c405927983d5b2ca3120aa9363d7d3.png", "Variations": 1, "Rarity": 11, "IsKnife": true, "ItemCollectionId": 24}, "Bayonet | Freehand": {"Name": "Bayonet | Freehand", "FloatMin": 0, "FloatMax": 48, "ImageUrl": "https://steamcdn-a.akamaihd.net/apps/730/icons/econ/default_generated/weapon_bayonet_am_marked_up_light_large.c2a4dbca9338c1a5ffaa246715696f92168a49bc.png", "Variations": 1, "Rarity": 11, "IsKnife": true, "ItemCollectionId": 24}, "Bayonet | Bright Water": {"Name": "Bayonet | Bright Water", "FloatMin": 0, "FloatMax": 50, "ImageUrl": "https://steamcdn-a.akamaihd.net/apps/730/icons/econ/default_generated/weapon_bayonet_hy_ocean_knife_light_large.d262ade9c249afcfbeeacf19deef49ccb0049c1a.png", "Variations": 1, "Rarity": 11, "IsKnife": true, "ItemCollectionId": 24}, "Flip Knife | Autotronic": {"Name": "Flip Knife | Autotronic", "FloatMin": 0, "FloatMax": 85, "ImageUrl": "https://steamcdn-a.akamaihd.net/apps/730/icons/econ/default_generated/weapon_knife_flip_gs_flip_autotronic_light_large.882d012ef1e758c9e323dd5d6202c49fbe894e05.png", "Variations": 1, "Rarity": 11, "IsKnife": true, "ItemCollectionId": 24}, "Flip Knife | Gamma Doppler": {"Name": "Flip Knife | Gamma Doppler", "FloatMin": 0, "FloatMax": 8, "ImageUrl": "https://steamcdn-a.akamaihd.net/apps/730/icons/econ/default_generated/weapon_knife_flip_am_gamma_doppler_phase1_light_large.7bf92c117841e553340bc5c0d0266cb458b92249.png", "Variations": 1, "Rarity": 11, "IsKnife": true, "ItemCollectionId": 24}, "Flip Knife | Lore": {"Name": "Flip Knife | Lore", "FloatMin": 0, "FloatMax": 65, "ImageUrl": "https://steamcdn-a.akamaihd.net/apps/730/icons/econ/default_generated/weapon_knife_flip_cu_flip_lore_light_large.df03b3186c105676470d2ac73e4bea375fedbf77.png", "Variations": 1, "Rarity": 11, "IsKnife": true, "ItemCollectionId": 24}, "Flip Knife | Bright Water": {"Name": "Flip Knife | Bright Water", "FloatMin": 0, "FloatMax": 50, "ImageUrl": "https://steamcdn-a.akamaihd.net/apps/730/icons/econ/default_generated/weapon_knife_flip_hy_ocean_knife_light_large.6d35f9bc8d0ab2da7112155cf37ef782e542ef31.png", "Variations": 1, "Rarity": 11, "IsKnife": true, "ItemCollectionId": 24}, "Flip Knife | Black Laminate": {"Name": "Flip Knife | Black Laminate", "FloatMin": 0, "FloatMax": 100, "ImageUrl": "https://steamcdn-a.akamaihd.net/apps/730/icons/econ/default_generated/weapon_knife_flip_cu_flip_stonewash_light_large.e6f71d193d2965b443ede7015911feedfea6e5a8.png", "Variations": 1, "Rarity": 11, "IsKnife": true, "ItemCollectionId": 24}, "Flip Knife | Freehand": {"Name": "Flip Knife | Freehand", "FloatMin": 0, "FloatMax": 48, "ImageUrl": "https://steamcdn-a.akamaihd.net/apps/730/icons/econ/default_generated/weapon_knife_flip_am_marked_up_light_large.6420438f1930c72f9aee1fb6d2e1e41238caf340.png", "Variations": 1, "Rarity": 11, "IsKnife": true, "ItemCollectionId": 24}, "Gut Knife | Lore": {"Name": "Gut Knife | Lore", "FloatMin": 0, "FloatMax": 65, "ImageUrl": "https://steamcdn-a.akamaihd.net/apps/730/icons/econ/default_generated/weapon_knife_gut_cu_gut_lore_light_large.5cf5a77978675bd3d276a86017e6d1fcacd7bf00.png", "Variations": 1, "Rarity": 11, "IsKnife": true, "ItemCollectionId": 24}, "Gut Knife | Gamma Doppler": {"Name": "Gut Knife | Gamma Doppler", "FloatMin": 0, "FloatMax": 8, "ImageUrl": "https://steamcdn-a.akamaihd.net/apps/730/icons/econ/default_generated/weapon_knife_gut_am_gamma_doppler_phase1_light_large.aa0ee6d430814b265636f404ab85553e71f3450d.png", "Variations": 1, "Rarity": 11, "IsKnife": true, "ItemCollectionId": 24}, "Gut Knife | Autotronic": {"Name": "Gut Knife | Autotronic", "FloatMin": 0, "FloatMax": 85, "ImageUrl": "https://steamcdn-a.akamaihd.net/apps/730/icons/econ/default_generated/weapon_knife_gut_gs_gut_autotronic_light_large.160e79d868da6ebb84c52e835aaf24ab9c6334f1.png", "Variations": 1, "Rarity": 11, "IsKnife": true, "ItemCollectionId": 24}, "Gut Knife | Black Laminate": {"Name": "Gut Knife | Black Laminate", "FloatMin": 0, "FloatMax": 100, "ImageUrl": "https://steamcdn-a.akamaihd.net/apps/730/icons/econ/default_generated/weapon_knife_gut_cu_gut_stonewash_light_large.52a1c223ee5d85ddb2242c75a67c1f2f49b0e0b9.png", "Variations": 1, "Rarity": 11, "IsKnife": true, "ItemCollectionId": 24}, "Gut Knife | Freehand": {"Name": "Gut Knife | Freehand", "FloatMin": 0, "FloatMax": 48, "ImageUrl": "https://steamcdn-a.akamaihd.net/apps/730/icons/econ/default_generated/weapon_knife_gut_am_marked_up_light_large.08dac4cfbf7b626df37bb2b6ffd3d07d2fc86988.png", "Variations": 1, "Rarity": 11, "IsKnife": true, "ItemCollectionId": 24}, "Gut Knife | Bright Water": {"Name": "Gut Knife | Bright Water", "FloatMin": 0, "FloatMax": 50, "ImageUrl": "https://steamcdn-a.akamaihd.net/apps/730/icons/econ/default_generated/weapon_knife_gut_hy_ocean_knife_light_large.649f890d55e6ee2987e988e44a0f52e1a5020486.png", "Variations": 1, "Rarity": 11, "IsKnife": true, "ItemCollectionId": 24}, "Karambit | Autotronic": {"Name": "Karambit | Autotronic", "FloatMin": 0, "FloatMax": 85, "ImageUrl": "https://steamcdn-a.akamaihd.net/apps/730/icons/econ/default_generated/weapon_knife_karambit_gs_karam_autotronic_light_large.5af6c108ce38f71f0964f1bbd06bc48c1d3e5462.png", "Variations": 1, "Rarity": 11, "IsKnife": true, "ItemCollectionId": 24}, "Karambit | Gamma Doppler": {"Name": "Karambit | Gamma Doppler", "FloatMin": 0, "FloatMax": 8, "ImageUrl": "https://steamcdn-a.akamaihd.net/apps/730/icons/econ/default_generated/weapon_knife_karambit_am_gamma_doppler_phase1_light_large.769cf2ab676ea2a7d7322c258f57bac8dca00336.png", "Variations": 1, "Rarity": 11, "IsKnife": true, "ItemCollectionId": 24}, "Karambit | Lore": {"Name": "Karambit | Lore", "FloatMin": 0, "FloatMax": 65, "ImageUrl": "https://steamcdn-a.akamaihd.net/apps/730/icons/econ/default_generated/weapon_knife_karambit_cu_karam_lore_light_large.7090aea57b3a2abd82e09f0cdb840ac72f41df73.png", "Variations": 1, "Rarity": 11, "IsKnife": true, "ItemCollectionId": 24}, "Karambit | Black Laminate": {"Name": "Karambit | Black Laminate", "FloatMin": 0, "FloatMax": 100, "ImageUrl": "https://steamcdn-a.akamaihd.net/apps/730/icons/econ/default_generated/weapon_knife_karambit_cu_karam_stonewash_light_large.a45dfc7db5703c23ef3e5733fcc4a7b2a9bf6d73.png", "Variations": 1, "Rarity": 11, "IsKnife": true, "ItemCollectionId": 24}, "Karambit | Freehand": {"Name": "Karambit | Freehand", "FloatMin": 0, "FloatMax": 48, "ImageUrl": "https://steamcdn-a.akamaihd.net/apps/730/icons/econ/default_generated/weapon_knife_karambit_am_marked_up_fine_light_large.8814a38afa2383489a723019fc9e6e43f021f047.png", "Variations": 1, "Rarity": 11, "IsKnife": true, "ItemCollectionId": 24}, "Karambit | Bright Water": {"Name": "Karambit | Bright Water", "FloatMin": 0, "FloatMax": 50, "ImageUrl": "https://steamcdn-a.akamaihd.net/apps/730/icons/econ/default_generated/weapon_knife_karambit_hy_ocean_knife_light_large.f108e6440259472084635566f62d7497b9d5ab51.png", "Variations": 1, "Rarity": 11, "IsKnife": true, "ItemCollectionId": 24}, "M9 Bayonet | Gamma Doppler": {"Name": "M9 Bayonet | Gamma Doppler", "FloatMin": 0, "FloatMax": 8, "ImageUrl": "https://steamcdn-a.akamaihd.net/apps/730/icons/econ/default_generated/weapon_knife_m9_bayonet_am_gamma_doppler_phase1_light_large.4980cb2bb09e19a48a04ae19a0e6353426e81cce.png", "Variations": 1, "Rarity": 11, "IsKnife": true, "ItemCollectionId": 24}, "M9 Bayonet | Autotronic": {"Name": "M9 Bayonet | Autotronic", "FloatMin": 0, "FloatMax": 85, "ImageUrl": "https://steamcdn-a.akamaihd.net/apps/730/icons/econ/default_generated/weapon_knife_m9_bayonet_gs_m9_bay_autotronic_light_large.f81f68f78b0b40717602fc88f62b4d7af346c430.png", "Variations": 1, "Rarity": 11, "IsKnife": true, "ItemCollectionId": 24}, "M9 Bayonet | Black Laminate": {"Name": "M9 Bayonet | Black Laminate", "FloatMin": 0, "FloatMax": 100, "ImageUrl": "https://steamcdn-a.akamaihd.net/apps/730/icons/econ/default_generated/weapon_knife_m9_bayonet_cu_m9_bay_stonewash_light_large.addebdf2a1eb13e40ff7102e7a918d116653414b.png", "Variations": 1, "Rarity": 11, "IsKnife": true, "ItemCollectionId": 24}, "M9 Bayonet | Lore": {"Name": "M9 Bayonet | Lore", "FloatMin": 0, "FloatMax": 65, "ImageUrl": "https://steamcdn-a.akamaihd.net/apps/730/icons/econ/default_generated/weapon_knife_m9_bayonet_cu_m9_bay_lore_light_large.b4bfa26d570d440ee4c04244605a81031909da2f.png", "Variations": 1, "Rarity": 11, "IsKnife": true, "ItemCollectionId": 24}, "M9 Bayonet | Bright Water": {"Name": "M9 Bayonet | Bright Water", "FloatMin": 0, "FloatMax": 50, "ImageUrl": "https://steamcdn-a.akamaihd.net/apps/730/icons/econ/default_generated/weapon_knife_m9_bayonet_hy_ocean_knife_90_light_large.7c349b48ff79eb591eaa741aff78a0e086feaa4d.png", "Variations": 1, "Rarity": 11, "IsKnife": true, "ItemCollectionId": 24}, "M9 Bayonet | Freehand": {"Name": "M9 Bayonet | Freehand", "FloatMin": 0, "FloatMax": 48, "ImageUrl": "https://steamcdn-a.akamaihd.net/apps/730/icons/econ/default_generated/weapon_knife_m9_bayonet_am_marked_up_90_light_large.30a346e62c77a9552fe7ce89eca7c44e018aafd5.png", "Variations": 1, "Rarity": 11, "IsKnife": true, "ItemCollectionId": 24}}, "SouvenirPackId": null, "SouvenirPackName": null, "SouvenirPackImg": null}