{"Case": "The Rising Sun Collection", "IsBuff": false, "IsSkinport": true, "ImageUrl": "https://steamcdn-a.akamaihd.net/apps/730/icons/econ/default_generated/weapon_aug_cu_anime_aug_light_large.f049075c645871ee67b0b47253f59c26143efc49.png", "Profit": 0.9992505657614483, "ProfitPercents": {"Covert": 0.00026624068157614486, "Classified": 0.0013310702875399363, "Restricted": 0.006612919329073484, "Mil_Spec": 0.03259784345047923, "Industrial": 0.15973642172523964, "Consumer": 0.7987060702875399}, "PercentReceive": {"Covert": 0.00026624068157614486, "Classified": 0.0013312034078807242, "Restricted": 0.006656017039403621, "Mil_Spec": 0.033280085197018104, "Industrial": 0.1597444089456869, "Consumer": 0.7987220447284346}, "CaseCost": 0.01, "KeyCost": 0, "ROI": 1133.7713003745869, "RarityROIPercents": {"Covert": 0.021151835729645803, "Classified": 0.12426645322102645, "Restricted": 0.13763354220150256, "Mil_Spec": 0.2911460549509457, "Industrial": 0.2583249395123879, "Consumer": 0.1674771743844916}, "RarityValue": {"Covert": 900.739291927162, "Classified": 1058.363713819193, "Restricted": 234.44194807971792, "Mil_Spec": 99.18635705603332, "Industrial": 18.33437580214317, "Consumer": 2.3773077885877805}, "IsCaseEstimate": false, "KnifeCosts": null, "ItemCosts": {"Covert": {"AUG | Akihabara Accept": {"FactoryNew": 5288.891900934199, "MinimalWear": 1489.3899999999999, "FieldTested": 757.9116588576, "WellWorn": 355.78, "BattleScarred": 307.00554672579995, "totalItemValue": 900.739291927162}}, "Classified": {"AK-47 | Hydroponic": {"FactoryNew": 1909.8054626325998, "MinimalWear": 1447.2133944892, "FieldTested": 925.4280355502, "WellWorn": 642.26, "BattleScarred": 556.7265795, "totalItemValue": 1058.363713819193}}, "Restricted": {"Five-SeveN | Neon Kimono": {"FactoryNew": 296.4118352416, "MinimalWear": 249.2014213, "FieldTested": 201.48200020000002, "WellWorn": 0, "BattleScarred": 181.757972812, "totalItemValue": 211.16713814818235}, "Desert Eagle | Sunset Storm \u5f10": {"FactoryNew": 243.07, "MinimalWear": 228.94, "FieldTested": 257.17586678159995, "WellWorn": 230.5272211762, "BattleScarred": 184.56811649899998, "totalItemValue": 239.5854858519143}, "Desert Eagle | Sunset Storm \u58f1": {"FactoryNew": 289.338756603, "MinimalWear": 233.96999999999997, "FieldTested": 266.5606862646, "WellWorn": 171.2490958542, "BattleScarred": 227.1656530676, "totalItemValue": 252.68873218391653}, "M4A4 | Daybreak": {"FactoryNew": 239.64999999999998, "MinimalWear": 243.8992634, "FieldTested": 233.241926021, "WellWorn": 213.01949579040001, "BattleScarred": 207.685524943, "totalItemValue": 234.3264361348585}}, "Mil_Spec": {"Galil AR | Aqua Terrace": {"FactoryNew": 104.08, "MinimalWear": 119.89239443479998, "FieldTested": 97.11, "WellWorn": 0, "BattleScarred": 98.72618009799999, "totalItemValue": 100.8554454069293}, "Tec-9 | Terrace": {"FactoryNew": 127.1351421262, "MinimalWear": 101.7802230484, "FieldTested": 100.74100010000001, "WellWorn": 92.44, "BattleScarred": 87.82494345559999, "totalItemValue": 97.723428781298}, "MAG-7 | Counter Terrace": {"FactoryNew": 99.67999999999999, "MinimalWear": 101.70599283779998, "FieldTested": 106.04315799999999, "WellWorn": 0, "BattleScarred": 86.3509435594, "totalItemValue": 98.98019697987262}}, "Industrial": {"Desert Eagle | Midnight Storm": {"FactoryNew": 26.3623290788, "MinimalWear": 19.3634806508, "FieldTested": 17.8258548598, "WellWorn": 19.0029339136, "BattleScarred": 18.7908475976, "totalItemValue": 19.01004092604916}, "P250 | Crimson Kimono": {"FactoryNew": 17.84, "MinimalWear": 20.254243178, "FieldTested": 16.086747068599998, "WellWorn": 19.8618834934, "BattleScarred": 18.504531071, "totalItemValue": 17.658710678237178}}, "Consumer": {"Tec-9 | Bamboo Forest": {"FactoryNew": 5.87, "MinimalWear": 3.605467372, "FieldTested": 1.9936113704, "WellWorn": 2.173884739, "BattleScarred": 1.8875682124, "totalItemValue": 2.9975798029104}, "PP-Bizon | Bamboo Print": {"FactoryNew": 4.6234816888, "MinimalWear": 2.7783307396000003, "FieldTested": 2.4283883182, "WellWorn": 2.6722875816, "BattleScarred": 1.73, "totalItemValue": 2.55562833366164}, "Sawed-Off | Bamboo Shadow": {"FactoryNew": 2.0360286336, "MinimalWear": 2.19, "FieldTested": 2.1102588442, "WellWorn": 2.4177840024, "BattleScarred": 1.79, "totalItemValue": 2.10570088655344}, "P250 | Mint Kimono": {"FactoryNew": 3.764532109, "MinimalWear": 2.332949476, "FieldTested": 1.9405897914, "WellWorn": 1.7200000000000002, "BattleScarred": 1.8239423176, "totalItemValue": 2.12140643072474}, "G3SG1 | Orange Kimono": {"FactoryNew": 3.24, "MinimalWear": 2.2693235812, "FieldTested": 1.961798423, "WellWorn": 1.71, "BattleScarred": 1.9724027388, "totalItemValue": 2.10622348908868}}}, "Items": {"AUG | Akihabara Accept": {"Name": "AUG | Akihabara Accept", "FloatMin": 0, "FloatMax": 100, "ImageUrl": "https://steamcdn-a.akamaihd.net/apps/730/icons/econ/default_generated/weapon_aug_cu_anime_aug_light_large.f049075c645871ee67b0b47253f59c26143efc49.png", "Variations": 0, "Rarity": 11, "IsKnife": false, "ItemCollectionId": 70}, "AK-47 | Hydroponic": {"Name": "AK-47 | Hydroponic", "FloatMin": 0, "FloatMax": 80, "ImageUrl": "https://steamcdn-a.akamaihd.net/apps/730/icons/econ/default_generated/weapon_ak47_am_bamboo_jungle_light_large.98cd023e9d2207ad765b600b281352cbc5009051.png", "Variations": 0, "Rarity": 8, "IsKnife": false, "ItemCollectionId": 70}, "Five-SeveN | Neon Kimono": {"Name": "Five-SeveN | Neon Kimono", "FloatMin": 0, "FloatMax": 80, "ImageUrl": "https://steamcdn-a.akamaihd.net/apps/730/icons/econ/default_generated/weapon_fiveseven_hy_kimono_diamonds_light_large.c82060a31b7e4b17c73eb76fd87c09037a3eba42.png", "Variations": 0, "Rarity": 5, "IsKnife": false, "ItemCollectionId": 70}, "Desert Eagle | Sunset Storm \u5f10": {"Name": "Desert Eagle | Sunset Storm \u5f10", "FloatMin": 0, "FloatMax": 75, "ImageUrl": "https://steamcdn-a.akamaihd.net/apps/730/icons/econ/default_generated/weapon_deagle_am_seastorm_shojo_light_large.7df4fe386dac18ae2a8c3e50df7dfb9165dece83.png", "Variations": 0, "Rarity": 5, "IsKnife": false, "ItemCollectionId": 70}, "Desert Eagle | Sunset Storm \u58f1": {"Name": "Desert Eagle | Sunset Storm \u58f1", "FloatMin": 0, "FloatMax": 75, "ImageUrl": "https://steamcdn-a.akamaihd.net/apps/730/icons/econ/default_generated/weapon_deagle_am_seastorm_blood_light_large.1e92a7e19fde014e5a70832a93b440e0c036d596.png", "Variations": 0, "Rarity": 5, "IsKnife": false, "ItemCollectionId": 70}, "M4A4 | Daybreak": {"Name": "M4A4 | Daybreak", "FloatMin": 0, "FloatMax": 60, "ImageUrl": "https://steamcdn-a.akamaihd.net/apps/730/icons/econ/default_generated/weapon_m4a1_am_kimono_sunrise_light_large.f4c4233632fed7004ab4666aeaceab53233cddd6.png", "Variations": 0, "Rarity": 5, "IsKnife": false, "ItemCollectionId": 70}, "Galil AR | Aqua Terrace": {"Name": "Galil AR | Aqua Terrace", "FloatMin": 0, "FloatMax": 70, "ImageUrl": "https://steamcdn-a.akamaihd.net/apps/730/icons/econ/default_generated/weapon_galilar_am_geometric_steps_light_large.fd64d3b26b97da3c03ab009e91d3f53c95e86cc0.png", "Variations": 0, "Rarity": 2, "IsKnife": false, "ItemCollectionId": 70}, "Tec-9 | Terrace": {"Name": "Tec-9 | Terrace", "FloatMin": 0, "FloatMax": 100, "ImageUrl": "https://steamcdn-a.akamaihd.net/apps/730/icons/econ/default_generated/weapon_tec9_hy_geometric_steps_yellow_light_large.4d50c678bf9eeb9f063a432aa9d5aec68e863f7d.png", "Variations": 0, "Rarity": 2, "IsKnife": false, "ItemCollectionId": 70}, "MAG-7 | Counter Terrace": {"Name": "MAG-7 | Counter Terrace", "FloatMin": 0, "FloatMax": 65, "ImageUrl": "https://steamcdn-a.akamaihd.net/apps/730/icons/econ/default_generated/weapon_mag7_hy_geometric_steps_green_light_large.542348e3effe63aae75b070cb1ca7d193e8356cf.png", "Variations": 0, "Rarity": 2, "IsKnife": false, "ItemCollectionId": 70}, "Desert Eagle | Midnight Storm": {"Name": "Desert Eagle | Midnight Storm", "FloatMin": 0, "FloatMax": 75, "ImageUrl": "https://steamcdn-a.akamaihd.net/apps/730/icons/econ/default_generated/weapon_deagle_am_seastorm_light_large.aef21efecda37237d24debe3f409f42954dadddd.png", "Variations": 0, "Rarity": 1, "IsKnife": false, "ItemCollectionId": 70}, "P250 | Crimson Kimono": {"Name": "P250 | Crimson Kimono", "FloatMin": 0, "FloatMax": 80, "ImageUrl": "https://steamcdn-a.akamaihd.net/apps/730/icons/econ/default_generated/weapon_p250_hy_kimono_diamonds_red_light_large.99ecb66f68d6bba4e17bc30cd72d5041e838371c.png", "Variations": 0, "Rarity": 1, "IsKnife": false, "ItemCollectionId": 70}, "Tec-9 | Bamboo Forest": {"Name": "Tec-9 | Bamboo Forest", "FloatMin": 0, "FloatMax": 60, "ImageUrl": "https://steamcdn-a.akamaihd.net/apps/730/icons/econ/default_generated/weapon_tec9_hy_bamboo_jungle_light_large.31268450fbb5b5c2221e6eaadbe7124cf85f3e1d.png", "Variations": 0, "Rarity": 0, "IsKnife": false, "ItemCollectionId": 70}, "PP-Bizon | Bamboo Print": {"Name": "PP-Bizon | Bamboo Print", "FloatMin": 0, "FloatMax": 80, "ImageUrl": "https://steamcdn-a.akamaihd.net/apps/730/icons/econ/default_generated/weapon_bizon_hy_bamboo_jungle_ink_light_large.0f9ee611e9b667e90923e9fc0da89430881ae7ae.png", "Variations": 0, "Rarity": 0, "IsKnife": false, "ItemCollectionId": 70}, "Sawed-Off | Bamboo Shadow": {"Name": "Sawed-Off | Bamboo Shadow", "FloatMin": 0, "FloatMax": 60, "ImageUrl": "https://steamcdn-a.akamaihd.net/apps/730/icons/econ/default_generated/weapon_sawedoff_hy_bamboo_jungle_black_light_large.8c345668f9d6ba961f72fd67c405a8ed2cfffd4c.png", "Variations": 0, "Rarity": 0, "IsKnife": false, "ItemCollectionId": 70}, "P250 | Mint Kimono": {"Name": "P250 | Mint Kimono", "FloatMin": 0, "FloatMax": 80, "ImageUrl": "https://steamcdn-a.akamaihd.net/apps/730/icons/econ/default_generated/weapon_p250_sp_kimono_diamonds_light_large.f8b2d66cdc64e8860b36ac2d08060d04e5ec6ae4.png", "Variations": 0, "Rarity": 0, "IsKnife": false, "ItemCollectionId": 70}, "G3SG1 | Orange Kimono": {"Name": "G3SG1 | Orange Kimono", "FloatMin": 0, "FloatMax": 80, "ImageUrl": "https://steamcdn-a.akamaihd.net/apps/730/icons/econ/default_generated/weapon_g3sg1_hy_kimono_diamonds_orange_light_large.bdab5d4f92f5733ed056bbe276761c377b5c3401.png", "Variations": 0, "Rarity": 0, "IsKnife": false, "ItemCollectionId": 70}}, "SouvenirPackId": null, "SouvenirPackName": null, "SouvenirPackImg": null}